{
    "AspectDefineClass" : ["UIColor"],
    "Aspects": [
        {
            "selName": "viewWillAppear:",
            "hookType": 3,
            "className": "ViewController",
            "argumentNames": ["animated"],
            "customMessages" : [
                {
                    "message" : "UIColor.lightGrayColor",
                    "messageType" : 0,
                    "localInstanceKey" : "lightGrayColor",
                    "invokeCondition": {
                        "condition" : "animated==0",
                        "operator" : "==",
                        "conditionKey" : "isAnimated"
                    }
                },
                {
                    "message" : "self.view.setBackgroundColor:",
                    "messageType" : 0,
                    "arguments" : {
                        "setBackgroundColor:" : [{
                            "index" : 0,
                            "value" : "lightGrayColor",
                            "type"  : 1
                        }]
                    },
                    "invokeCondition": {
                        "conditionKey" : "isAnimated"
                    }
                }

            ],
            "ApplySystemVersions": [
                "*"
            ]
        }
    ]
}
